awdx/__init__.py
awdx/__main__.py
awdx/cli.py
awdx/ai_engine/__init__.py
awdx/ai_engine/ai_commands.py
awdx/ai_engine/config_manager.py
awdx/ai_engine/exceptions.py
awdx/ai_engine/gemini_client.py
awdx/ai_engine/nlp_processor.py
awdx/costlyzer/__init__.py
awdx/costlyzer/cost_commands.py
awdx/iamply/__init__.py
awdx/iamply/iam_commands.py
awdx/mcp_server/__init__.py
awdx/mcp_server/cli.py
awdx/mcp_server/server.py
awdx/mcp_server/tools.py
awdx/profilyze/__init__.py
awdx/profilyze/profile_commands.py
awdx/s3ntry/__init__.py
awdx/s3ntry/s3_commands.py
awdx/secrex/__init__.py
awdx/secrex/secret_commands.py
awdx/secutide/__init__.py
awdx/secutide/security_commands.py
awdx/task/__init__.py
awdx/task/intents.py
awdx/task/task_commands.py
awdx-0.0.16.dist-info/licenses/AUTHORS.md
awdx-0.0.16.dist-info/licenses/LICENSE
awdx-0.0.16.dist-info/METADATA
awdx-0.0.16.dist-info/WHEEL
awdx-0.0.16.dist-info/entry_points.txt
awdx-0.0.16.dist-info/top_level.txt
awdx-0.0.16.dist-info/RECORD
