Metadata-Version: 2.4
Name: awdx
Version: 0.0.16
Summary: AWS DevOps X: Gen AI-powered AWS DevSecOps CLI tool with natural language interface.
Author-email: Partha Sarathi Kundu <inboxkundu@gmail.com>
Maintainer-email: Partha Sarathi Kundu <inboxkundu@gmail.com>
License-Expression: MIT
Project-URL: Homepage, https://github.com/pxkundu/awdx
Project-URL: Repository, https://github.com/pxkundu/awdx
Keywords: aws,devops,devsecops,cli,cost-analysis,security,automation,ai,nlp,gemini,natural-language
Classifier: Development Status :: 3 - Alpha
Classifier: Intended Audience :: Developers
Classifier: Intended Audience :: System Administrators
Classifier: Operating System :: OS Independent
Classifier: Programming Language :: Python :: 3
Classifier: Programming Language :: Python :: 3.8
Classifier: Programming Language :: Python :: 3.9
Classifier: Programming Language :: Python :: 3.10
Classifier: Programming Language :: Python :: 3.11
Classifier: Programming Language :: Python :: 3.12
Classifier: Programming Language :: Python :: 3.13
Classifier: Topic :: System :: Systems Administration
Classifier: Topic :: Utilities
Classifier: Topic :: Software Development :: Libraries :: Python Modules
Requires-Python: >=3.8
License-File: LICENSE
License-File: AUTHORS.md
Requires-Dist: typer[all]>=0.9.0
Requires-Dist: boto3>=1.28.0
Requires-Dist: google-generativeai>=0.3.0
Requires-Dist: rich>=13.0.0
Requires-Dist: pyyaml>=6.0
Requires-Dist: pillow>=9.0.0
Requires-Dist: importlib-metadata>=4.0.0; python_version < "3.8"
Provides-Extra: dev
Requires-Dist: pytest>=7.0.0; extra == "dev"
Requires-Dist: pytest-cov>=4.0.0; extra == "dev"
Requires-Dist: pytest-asyncio>=0.21.0; extra == "dev"
Requires-Dist: pytest-mock>=3.10.0; extra == "dev"
Provides-Extra: security
Requires-Dist: bandit[toml]>=1.7.0; extra == "security"
Requires-Dist: safety>=3.0.0; extra == "security"
Requires-Dist: flake8>=6.0.0; extra == "security"
Requires-Dist: mypy>=1.0.0; extra == "security"
Requires-Dist: black>=23.0.0; extra == "security"
Requires-Dist: isort>=5.12.0; extra == "security"
Requires-Dist: pylint>=3.0.0; extra == "security"
Provides-Extra: test
Requires-Dist: pytest>=7.0.0; extra == "test"
Requires-Dist: pytest-cov>=4.0.0; extra == "test"
Requires-Dist: pytest-asyncio>=0.21.0; extra == "test"
Requires-Dist: pytest-mock>=3.10.0; extra == "test"
Requires-Dist: bandit[toml]>=1.7.0; extra == "test"
Requires-Dist: safety>=3.0.0; extra == "test"
Requires-Dist: flake8>=6.0.0; extra == "test"
Requires-Dist: mypy>=1.0.0; extra == "test"
Requires-Dist: black>=23.0.0; extra == "test"
Requires-Dist: isort>=5.12.0; extra == "test"
Requires-Dist: pylint>=3.0.0; extra == "test"
Requires-Dist: moto[all]>=4.0.0; extra == "test"
Requires-Dist: types-PyYAML>=6.0.0; extra == "test"
Dynamic: license-file
